kaggle_deps/__init__.py
kaggle_deps-0.1.0.dist-info/METADATA
kaggle_deps-0.1.0.dist-info/WHEEL
kaggle_deps-0.1.0.dist-info/top_level.txt
kaggle_deps-0.1.0.dist-info/RECORD
