Metadata-Version: 2.4
Name: kaggle_deps
Version: 0.1.0
Author: mehtab
Author-email: arbabali000001@gmail.com
Requires-Dist: fsspec==2023.9.1
Requires-Dist: huggingface_hub==0.17.3
Requires-Dist: datasets==2.13.1
Requires-Dist: torch==2.0.1
Requires-Dist: torchvision==0.15.2
Requires-Dist: torchaudio==2.0.2
Requires-Dist: transformers==4.30.1
Requires-Dist: evaluate==0.4.0
Requires-Dist: accelerate==0.21.0
Requires-Dist: gradio==3.34.0
Requires-Dist: rouge-score==0.1.2
Requires-Dist: bert-score==0.3.13
Requires-Dist: pyarrow==11.0.0
Requires-Dist: pandas==1.5.3
Requires-Dist: timm==0.9.2
Requires-Dist: cloud-tpu-client==0.10
Requires-Dist: kagglehub[pandas-datasets]==0.3.12
Requires-Dist: tokenizers==0.13.3
Dynamic: author
Dynamic: author-email
Dynamic: requires-dist
